setup.py
pgdumper/__init__.py
pgdumper/pgdumper.py
pgdumper.egg-info/PKG-INFO
pgdumper.egg-info/SOURCES.txt
pgdumper.egg-info/dependency_links.txt
pgdumper.egg-info/entry_points.txt
pgdumper.egg-info/requires.txt
pgdumper.egg-info/top_level.txt