Metadata-Version: 1.1
Name: pgdumper
Version: 0.1
Summary: Simple PostgreSQL dumper
Home-page: https://github.com/rdolgushin/pgdumper
Author: Roman Dolgushin
Author-email: rd@roman-dolgushin.ru
License: MIT
Platform: UNKNOWN
Classifier: Topic :: Utilities
Classifier: Topic :: Database
Classifier: Topic :: System :: Systems Administration
Classifier: Environment :: Console
Classifier: License :: OSI Approved :: MIT License
Classifier: Operating System :: POSIX
